magbotsim/__init__.py
magbotsim/basic_magbot_env.py
magbotsim/assets/meshes/mover_and_bumper/beckhoff_apm4220_bumper.stl
magbotsim/assets/meshes/mover_and_bumper/beckhoff_apm4220_mover.stl
magbotsim/assets/meshes/mover_and_bumper/beckhoff_apm4330_bumper.stl
magbotsim/assets/meshes/mover_and_bumper/beckhoff_apm4330_mover.stl
magbotsim/assets/meshes/mover_and_bumper/beckhoff_apm4550_bumper.stl
magbotsim/assets/meshes/mover_and_bumper/beckhoff_apm4550_mover.stl
magbotsim/assets/meshes/mover_and_bumper/planar_motor_M3-15-SD.stl
magbotsim/assets/meshes/mover_and_bumper/planar_motor_M3-25-SD.stl
magbotsim/assets/meshes/mover_and_bumper/planar_motor_M4-11-SD.stl
magbotsim/assets/meshes/mover_and_bumper/planar_motor_M4-18-SD.stl
magbotsim/assets/meshes/mover_and_bumper/planar_motor_M4-33-SD.stl
magbotsim/assets/meshes/robot_arms/franka_emika_panda/collision/hand.stl
magbotsim/assets/meshes/robot_arms/franka_emika_panda/collision/link0.stl
magbotsim/assets/meshes/robot_arms/franka_emika_panda/collision/link1.stl
magbotsim/assets/meshes/robot_arms/franka_emika_panda/collision/link2.stl
magbotsim/assets/meshes/robot_arms/franka_emika_panda/collision/link3.stl
magbotsim/assets/meshes/robot_arms/franka_emika_panda/collision/link4.stl
magbotsim/assets/meshes/robot_arms/franka_emika_panda/collision/link5.stl
magbotsim/assets/meshes/robot_arms/franka_emika_panda/collision/link5_collision_0.obj
magbotsim/assets/meshes/robot_arms/franka_emika_panda/collision/link5_collision_1.obj
magbotsim/assets/meshes/robot_arms/franka_emika_panda/collision/link5_collision_2.obj
magbotsim/assets/meshes/robot_arms/franka_emika_panda/collision/link6.stl
magbotsim/assets/meshes/robot_arms/franka_emika_panda/collision/link7.stl
magbotsim/assets/meshes/robot_arms/franka_emika_panda/visual/finger_0.obj
magbotsim/assets/meshes/robot_arms/franka_emika_panda/visual/finger_1.obj
magbotsim/assets/meshes/robot_arms/franka_emika_panda/visual/hand_0.obj
magbotsim-1.0.0.dist-info/licenses/LICENSE
magbotsim-1.0.0.dist-info/METADATA
magbotsim-1.0.0.dist-info/WHEEL
magbotsim-1.0.0.dist-info/entry_points.txt
magbotsim-1.0.0.dist-info/top_level.txt
magbotsim-1.0.0.dist-info/RECORD
