Metadata-Version: 2.4
Name: magbotsim
Version: 1.0.0
Summary: Magentic robotics simulation including reinforcement learning environments based on MuJoCo
Author-email: Lara Bergmann <lara.bergmann@uni-bielefeld.de>
Project-URL: Homepage, https://www.uni-bielefeld.de/fakultaeten/technische-fakultaet/arbeitsgruppen/kollaborative-robotik/
Project-URL: Repository, https://github.com/ubi-coro/MagBotSim
Project-URL: Documentation, https://ubi-coro.github.io/MagBotSim/
Keywords: Magnetic Robotics,Reinforcement Learning,Gymnasium,PettingZoo,RL,AI,Robotics,Magnetic Levitation
Classifier: Development Status :: 5 - Production/Stable
Classifier: License :: OSI Approved :: GNU General Public License v3 (GPLv3)
Classifier: Programming Language :: Python :: 3.11
Classifier: Programming Language :: Python :: 3.12
Classifier: Programming Language :: Python :: 3.13
Classifier: Intended Audience :: Science/Research
Classifier: Topic :: Scientific/Engineering :: Artificial Intelligence
Requires-Python: <3.14,>=3.11
License-File: LICENSE
Requires-Dist: numpy
Requires-Dist: matplotlib
Requires-Dist: gymnasium>=0.29.1
Requires-Dist: pettingzoo
Requires-Dist: mujoco>=3.1.2
Requires-Dist: imageio
Requires-Dist: scipy
Requires-Dist: shapely
Provides-Extra: manual-control
Requires-Dist: pygame; extra == "manual-control"
Provides-Extra: tests
Requires-Dist: pytest; extra == "tests"
Requires-Dist: ruff; extra == "tests"
Provides-Extra: docs
Requires-Dist: sphinx; extra == "docs"
Requires-Dist: sphinx-autobuild; extra == "docs"
Requires-Dist: sphinxcontrib.spelling; extra == "docs"
Requires-Dist: pydata-sphinx-theme; extra == "docs"
Requires-Dist: sphinx-copybutton; extra == "docs"
Requires-Dist: sphinxcontrib-video; extra == "docs"
Dynamic: license-file
